ea2p/__init__.py
ea2p/src/__init__.py
ea2p/src/amd.py
ea2p/src/intel.py
ea2p/src/nvidia.py
ea2p/src/power.py
ea2p/src/power_meter.py
ea2p/src/power_meter_mpi.py
ea2p/src/ram.py
ea2p/src/utils.py
ea2p/src/wrapper.py
EA2P-1.0.1.dist-info/LICENSE
EA2P-1.0.1.dist-info/METADATA
EA2P-1.0.1.dist-info/WHEEL
EA2P-1.0.1.dist-info/top_level.txt
EA2P-1.0.1.dist-info/RECORD
