Metadata-Version: 2.1
Name: EA2P
Version: 1.0.1
Summary: EA2P (Energy-Aware Application Profiler): A multi-platform profiling tool that offers precise and detailed energy usage measurements for applications, with the ability to adapt to different needs.
Home-page: https://github.com/HPC-CRI/EA2P
Author: Roblex NANA
Author-email: nanatchakouteroblex@email.com
Classifier: Programming Language :: Python :: 3
License-File: LICENSE
Requires-Dist: numpy
Requires-Dist: pandas
Requires-Dist: py-cpuinfo
Requires-Dist: psutil
Requires-Dist: requests
